README.md
setup.py
pusher_chatkit/__init__.py
pusher_chatkit/client.py
pusher_chatkit/constants.py
pusher_chatkit/exceptions.py
pusher_chatkit/pusher_chatkit.py
pusher_chatkit/version.py
pusher_chatkit/backends/Requests.py
pusher_chatkit/backends/Tornado.py
pusher_chatkit/backends/__init__.py
pusher_chatkit_server.egg-info/PKG-INFO
pusher_chatkit_server.egg-info/SOURCES.txt
pusher_chatkit_server.egg-info/dependency_links.txt
pusher_chatkit_server.egg-info/requires.txt
pusher_chatkit_server.egg-info/top_level.txt