Metadata-Version: 2.1
Name: pusher-chatkit-server
Version: 1.0.4
Summary: A Python library to interact with the Pusher Chatkit API
Home-page: https://github.com/zikphil/chatkit-server-python
Author: Philippe Labat
Author-email: philippe@labat.ca
License: MIT
Platform: UNKNOWN
Classifier: License :: OSI Approved :: MIT License
Classifier: Programming Language :: Python
Classifier: Development Status :: 4 - Beta
Classifier: Intended Audience :: Developers
Classifier: Topic :: Internet :: WWW/HTTP
Classifier: Programming Language :: Python :: 2
Classifier: Programming Language :: Python :: 3
Provides-Extra: tornado
